[
  {
    "id": "lectura-0001",
    "sensorId": "sensor-001",
    "division": "División El Teniente",
    "timestamp": "2025-08-01T12:00:23.000Z",
    "valor": 32.083,
    "unidad": "L",
    "tipo": "consumo_diesel",
    "participaEnCalculos": true,
    "anomalia": false,
    "motivos": [],
    "scoreAnomalia": 0,
    "valida": {
      "estado": "pendiente",
      "usuario": null,
      "comentario": null,
      "fecha": null
    },
    "historialValidaciones": [],
    "origen": "historico"
  },
  {
    "id": "lectura-0002",
    "sensorId": "sensor-001",
    "division": "División El Teniente",
    "timestamp": "2025-08-01T12:05:37.000Z",
    "valor": 31.766,
    "unidad": "L",
    "tipo": "consumo_diesel",
    "participaEnCalculos": true,
    "anomalia": false,
    "motivos": [],
    "scoreAnomalia": 0,
    "valida": {
      "estado": "pendiente",
      "usuario": null,
      "comentario": null,
      "fecha": null
    },
    "historialValidaciones": [],
    "origen": "historico"
  },
  {
    "id": "lectura-0003",
    "sensorId": "sensor-001",
    "division": "División El Teniente",
    "timestamp": "2025-08-01T12:10:33.000Z",
    "valor": 32.659,
    "unidad": "L",
    "tipo": "consumo_diesel",
    "participaEnCalculos": true,
    "anomalia": false,
    "motivos": [],
    "scoreAnomalia": 0,
    "valida": {
      "estado": "pendiente",
      "usuario": null,
      "comentario": null,
      "fecha": null
    },
    "historialValidaciones": [],
    "origen": "historico"
  },
  {
    "id": "lectura-0004",
    "sensorId": "sensor-001",
    "division": "División El Teniente",
    "timestamp": "2025-08-01T12:15:12.000Z",
    "valor": 31.91,
    "unidad": "L",
    "tipo": "consumo_diesel",
    "participaEnCalculos": true,
    "anomalia": false,
    "motivos": [],
    "scoreAnomalia": 0,
    "valida": {
      "estado": "pendiente",
      "usuario": null,
      "comentario": null,
      "fecha": null
    },
    "historialValidaciones": [],
    "origen": "historico"
  },
  {
    "id": "lectura-0005",
    "sensorId": "sensor-001",
    "division": "División El Teniente",
    "timestamp": "2025-08-01T12:20:15.000Z",
    "valor": 31.819,
    "unidad": "L",
    "tipo": "consumo_diesel",
    "participaEnCalculos": true,
    "anomalia": false,
    "motivos": [],
    "scoreAnomalia": 0,
    "valida": {
      "estado": "pendiente",
      "usuario": null,
      "comentario": null,
      "fecha": null
    },
    "historialValidaciones": [],
    "origen": "historico"
  },
  {
    "id": "lectura-0006",
    "sensorId": "sensor-001",
    "division": "División El Teniente",
    "timestamp": "2025-08-01T12:25:33.000Z",
    "valor": 37.75,
    "unidad": "L",
    "tipo": "consumo_diesel",
    "participaEnCalculos": true,
    "anomalia": false,
    "motivos": [],
    "scoreAnomalia": 0,
    "valida": {
      "estado": "pendiente",
      "usuario": null,
      "comentario": null,
      "fecha": null
    },
    "historialValidaciones": [],
    "origen": "historico"
  },
  {
    "id": "lectura-0007",
    "sensorId": "sensor-001",
    "division": "División El Teniente",
    "timestamp": "2025-08-01T12:30:28.000Z",
    "valor": 32.131,
    "unidad": "L",
    "tipo": "consumo_diesel",
    "participaEnCalculos": true,
    "anomalia": false,
    "motivos": [],
    "scoreAnomalia": 0,
    "valida": {
      "estado": "pendiente",
      "usuario": null,
      "comentario": null,
      "fecha": null
    },
    "historialValidaciones": [],
    "origen": "historico"
  },
  {
    "id": "lectura-0008",
    "sensorId": "sensor-001",
    "division": "División El Teniente",
    "timestamp": "2025-08-01T12:35:41.000Z",
    "valor": 31.822,
    "unidad": "L",
    "tipo": "consumo_diesel",
    "participaEnCalculos": true,
    "anomalia": false,
    "motivos": [],
    "scoreAnomalia": 0,
    "valida": {
      "estado": "pendiente",
      "usuario": null,
      "comentario": null,
      "fecha": null
    },
    "historialValidaciones": [],
    "origen": "historico"
  },
  {
    "id": "lectura-0009",
    "sensorId": "sensor-001",
    "division": "División El Teniente",
    "timestamp": "2025-08-01T12:40:29.000Z",
    "valor": 32.281,
    "unidad": "L",
    "tipo": "consumo_diesel",
    "participaEnCalculos": true,
    "anomalia": false,
    "motivos": [],
    "scoreAnomalia": 0,
    "valida": {
      "estado": "pendiente",
      "usuario": null,
      "comentario": null,
      "fecha": null
    },
    "historialValidaciones": [],
    "origen": "historico"
  },
  {
    "id": "lectura-0010",
    "sensorId": "sensor-001",
    "division": "División El Teniente",
    "timestamp": "2025-08-01T12:45:09.000Z",
    "valor": 32.48,
    "unidad": "L",
    "tipo": "consumo_diesel",
    "participaEnCalculos": true,
    "anomalia": false,
    "motivos": [],
    "scoreAnomalia": 0,
    "valida": {
      "estado": "pendiente",
      "usuario": null,
      "comentario": null,
      "fecha": null
    },
    "historialValidaciones": [],
    "origen": "historico"
  },
  {
    "id": "lectura-0011",
    "sensorId": "sensor-001",
    "division": "División El Teniente",
    "timestamp": "2025-08-01T12:50:28.000Z",
    "valor": 32.055,
    "unidad": "L",
    "tipo": "consumo_diesel",
    "participaEnCalculos": true,
    "anomalia": false,
    "motivos": [],
    "scoreAnomalia": 0,
    "valida": {
      "estado": "pendiente",
      "usuario": null,
      "comentario": null,
      "fecha": null
    },
    "historialValidaciones": [],
    "origen": "historico"
  },
  {
    "id": "lectura-0012",
    "sensorId": "sensor-001",
    "division": "División El Teniente",
    "timestamp": "2025-08-01T12:55:04.000Z",
    "valor": 31.822,
    "unidad": "L",
    "tipo": "consumo_diesel",
    "participaEnCalculos": true,
    "anomalia": false,
    "motivos": [],
    "scoreAnomalia": 0,
    "valida": {
      "estado": "pendiente",
      "usuario": null,
      "comentario": null,
      "fecha": null
    },
    "historialValidaciones": [],
    "origen": "historico"
  },
  {
    "id": "lectura-0013",
    "sensorId": "sensor-001",
    "division": "División El Teniente",
    "timestamp": "2025-08-01T13:00:48.000Z",
    "valor": 26.5,
    "unidad": "L",
    "tipo": "consumo_diesel",
    "participaEnCalculos": true,
    "anomalia": false,
    "motivos": [],
    "scoreAnomalia": 0,
    "valida": {
      "estado": "pendiente",
      "usuario": null,
      "comentario": null,
      "fecha": null
    },
    "historialValidaciones": [],
    "origen": "historico"
  },
  {
    "id": "lectura-0014",
    "sensorId": "sensor-001",
    "division": "División El Teniente",
    "timestamp": "2025-08-01T13:05:42.000Z",
    "valor": 32.399,
    "unidad": "L",
    "tipo": "consumo_diesel",
    "participaEnCalculos": true,
    "anomalia": false,
    "motivos": [],
    "scoreAnomalia": 0,
    "valida": {
      "estado": "pendiente",
      "usuario": null,
      "comentario": null,
      "fecha": null
    },
    "historialValidaciones": [],
    "origen": "historico"
  },
  {
    "id": "lectura-0015",
    "sensorId": "sensor-001",
    "division": "División El Teniente",
    "timestamp": "2025-08-01T13:10:05.000Z",
    "valor": 32.838,
    "unidad": "L",
    "tipo": "consumo_diesel",
    "participaEnCalculos": true,
    "anomalia": false,
    "motivos": [],
    "scoreAnomalia": 0,
    "valida": {
      "estado": "pendiente",
      "usuario": null,
      "comentario": null,
      "fecha": null
    },
    "historialValidaciones": [],
    "origen": "historico"
  },
  {
    "id": "lectura-0016",
    "sensorId": "sensor-001",
    "division": "División El Teniente",
    "timestamp": "2025-08-01T13:15:19.000Z",
    "valor": 32.821,
    "unidad": "L",
    "tipo": "consumo_diesel",
    "participaEnCalculos": true,
    "anomalia": false,
    "motivos": [],
    "scoreAnomalia": 0,
    "valida": {
      "estado": "pendiente",
      "usuario": null,
      "comentario": null,
      "fecha": null
    },
    "historialValidaciones": [],
    "origen": "historico"
  },
  {
    "id": "lectura-0017",
    "sensorId": "sensor-001",
    "division": "División El Teniente",
    "timestamp": "2025-08-01T13:20:21.000Z",
    "valor": 32.007,
    "unidad": "L",
    "tipo": "consumo_diesel",
    "participaEnCalculos": true,
    "anomalia": false,
    "motivos": [],
    "scoreAnomalia": 0,
    "valida": {
      "estado": "pendiente",
      "usuario": null,
      "comentario": null,
      "fecha": null
    },
    "historialValidaciones": [],
    "origen": "historico"
  },
  {
    "id": "lectura-0018",
    "sensorId": "sensor-001",
    "division": "División El Teniente",
    "timestamp": "2025-08-01T13:25:43.000Z",
    "valor": 31.891,
    "unidad": "L",
    "tipo": "consumo_diesel",
    "participaEnCalculos": true,
    "anomalia": false,
    "motivos": [],
    "scoreAnomalia": 0,
    "valida": {
      "estado": "pendiente",
      "usuario": null,
      "comentario": null,
      "fecha": null
    },
    "historialValidaciones": [],
    "origen": "historico"
  },
  {
    "id": "lectura-0019",
    "sensorId": "sensor-001",
    "division": "División El Teniente",
    "timestamp": "2025-08-01T13:30:07.000Z",
    "valor": 33.4,
    "unidad": "L",
    "tipo": "consumo_diesel",
    "participaEnCalculos": true,
    "anomalia": false,
    "motivos": [],
    "scoreAnomalia": 0,
    "valida": {
      "estado": "pendiente",
      "usuario": null,
      "comentario": null,
      "fecha": null
    },
    "historialValidaciones": [],
    "origen": "historico"
  },
  {
    "id": "lectura-0020",
    "sensorId": "sensor-001",
    "division": "División El Teniente",
    "timestamp": "2025-08-01T13:35:49.000Z",
    "valor": 32.26,
    "unidad": "L",
    "tipo": "consumo_diesel",
    "participaEnCalculos": true,
    "anomalia": false,
    "motivos": [],
    "scoreAnomalia": 0,
    "valida": {
      "estado": "pendiente",
      "usuario": null,
      "comentario": null,
      "fecha": null
    },
    "historialValidaciones": [],
    "origen": "historico"
  },
  {
    "id": "lectura-0021",
    "sensorId": "sensor-001",
    "division": "División El Teniente",
    "timestamp": "2025-08-01T13:40:27.000Z",
    "valor": 33.015,
    "unidad": "L",
    "tipo": "consumo_diesel",
    "participaEnCalculos": true,
    "anomalia": false,
    "motivos": [],
    "scoreAnomalia": 0,
    "valida": {
      "estado": "pendiente",
      "usuario": null,
      "comentario": null,
      "fecha": null
    },
    "historialValidaciones": [],
    "origen": "historico"
  },
  {
    "id": "lectura-0022",
    "sensorId": "sensor-001",
    "division": "División El Teniente",
    "timestamp": "2025-08-01T13:45:18.000Z",
    "valor": 32.888,
    "unidad": "L",
    "tipo": "consumo_diesel",
    "participaEnCalculos": true,
    "anomalia": false,
    "motivos": [],
    "scoreAnomalia": 0,
    "valida": {
      "estado": "pendiente",
      "usuario": null,
      "comentario": null,
      "fecha": null
    },
    "historialValidaciones": [],
    "origen": "historico"
  },
  {
    "id": "lectura-0023",
    "sensorId": "sensor-001",
    "division": "División El Teniente",
    "timestamp": "2025-08-01T13:50:25.000Z",
    "valor": 40,
    "unidad": "L",
    "tipo": "consumo_diesel",
    "participaEnCalculos": true,
    "anomalia": false,
    "motivos": [],
    "scoreAnomalia": 0,
    "valida": {
      "estado": "pendiente",
      "usuario": null,
      "comentario": null,
      "fecha": null
    },
    "historialValidaciones": [],
    "origen": "historico"
  },
  {
    "id": "lectura-0024",
    "sensorId": "sensor-001",
    "division": "División El Teniente",
    "timestamp": "2025-08-01T13:55:41.000Z",
    "valor": 32.05,
    "unidad": "L",
    "tipo": "consumo_diesel",
    "participaEnCalculos": true,
    "anomalia": false,
    "motivos": [],
    "scoreAnomalia": 0,
    "valida": {
      "estado": "pendiente",
      "usuario": null,
      "comentario": null,
      "fecha": null
    },
    "historialValidaciones": [],
    "origen": "historico"
  },
  {
    "id": "lectura-0025",
    "sensorId": "sensor-001",
    "division": "División El Teniente",
    "timestamp": "2025-08-01T14:00:30.000Z",
    "valor": 32.57,
    "unidad": "L",
    "tipo": "consumo_diesel",
    "participaEnCalculos": true,
    "anomalia": false,
    "motivos": [],
    "scoreAnomalia": 0,
    "valida": {
      "estado": "pendiente",
      "usuario": null,
      "comentario": null,
      "fecha": null
    },
    "historialValidaciones": [],
    "origen": "historico"
  },
  {
    "id": "lectura-0026",
    "sensorId": "sensor-001",
    "division": "División El Teniente",
    "timestamp": "2025-08-01T14:05:36.000Z",
    "valor": 32.851,
    "unidad": "L",
    "tipo": "consumo_diesel",
    "participaEnCalculos": true,
    "anomalia": false,
    "motivos": [],
    "scoreAnomalia": 0,
    "valida": {
      "estado": "pendiente",
      "usuario": null,
      "comentario": null,
      "fecha": null
    },
    "historialValidaciones": [],
    "origen": "historico"
  },
  {
    "id": "lectura-0027",
    "sensorId": "sensor-001",
    "division": "División El Teniente",
    "timestamp": "2025-08-01T14:10:19.000Z",
    "valor": 32.313,
    "unidad": "L",
    "tipo": "consumo_diesel",
    "participaEnCalculos": true,
    "anomalia": false,
    "motivos": [],
    "scoreAnomalia": 0,
    "valida": {
      "estado": "pendiente",
      "usuario": null,
      "comentario": null,
      "fecha": null
    },
    "historialValidaciones": [],
    "origen": "historico"
  },
  {
    "id": "lectura-0028",
    "sensorId": "sensor-001",
    "division": "División El Teniente",
    "timestamp": "2025-08-01T14:15:31.000Z",
    "valor": 25,
    "unidad": "L",
    "tipo": "consumo_diesel",
    "participaEnCalculos": true,
    "anomalia": false,
    "motivos": [],
    "scoreAnomalia": 0,
    "valida": {
      "estado": "pendiente",
      "usuario": null,
      "comentario": null,
      "fecha": null
    },
    "historialValidaciones": [],
    "origen": "historico"
  },
  {
    "id": "lectura-0029",
    "sensorId": "sensor-001",
    "division": "División El Teniente",
    "timestamp": "2025-08-01T14:20:44.000Z",
    "valor": 32.25,
    "unidad": "L",
    "tipo": "consumo_diesel",
    "participaEnCalculos": true,
    "anomalia": false,
    "motivos": [],
    "scoreAnomalia": 0,
    "valida": {
      "estado": "pendiente",
      "usuario": null,
      "comentario": null,
      "fecha": null
    },
    "historialValidaciones": [],
    "origen": "historico"
  },
  {
    "id": "lectura-0030",
    "sensorId": "sensor-001",
    "division": "División El Teniente",
    "timestamp": "2025-08-01T14:25:46.000Z",
    "valor": 31.857,
    "unidad": "L",
    "tipo": "consumo_diesel",
    "participaEnCalculos": true,
    "anomalia": false,
    "motivos": [],
    "scoreAnomalia": 0,
    "valida": {
      "estado": "pendiente",
      "usuario": null,
      "comentario": null,
      "fecha": null
    },
    "historialValidaciones": [],
    "origen": "historico"
  },
  {
    "id": "lectura-0031",
    "sensorId": "sensor-002",
    "division": "Chuquicamata",
    "timestamp": "2025-08-01T12:00:04.000Z",
    "valor": 1280.133,
    "unidad": "kWh",
    "tipo": "energia_kwh",
    "participaEnCalculos": true,
    "anomalia": false,
    "motivos": [],
    "scoreAnomalia": 0,
    "valida": {
      "estado": "pendiente",
      "usuario": null,
      "comentario": null,
      "fecha": null
    },
    "historialValidaciones": [],
    "origen": "historico"
  },
  {
    "id": "lectura-0032",
    "sensorId": "sensor-002",
    "division": "Chuquicamata",
    "timestamp": "2025-08-01T12:10:36.000Z",
    "valor": 1272.828,
    "unidad": "kWh",
    "tipo": "energia_kwh",
    "participaEnCalculos": true,
    "anomalia": false,
    "motivos": [],
    "scoreAnomalia": 0,
    "valida": {
      "estado": "pendiente",
      "usuario": null,
      "comentario": null,
      "fecha": null
    },
    "historialValidaciones": [],
    "origen": "historico"
  },
  {
    "id": "lectura-0033",
    "sensorId": "sensor-002",
    "division": "Chuquicamata",
    "timestamp": "2025-08-01T12:20:08.000Z",
    "valor": 1265.672,
    "unidad": "kWh",
    "tipo": "energia_kwh",
    "participaEnCalculos": true,
    "anomalia": false,
    "motivos": [],
    "scoreAnomalia": 0,
    "valida": {
      "estado": "pendiente",
      "usuario": null,
      "comentario": null,
      "fecha": null
    },
    "historialValidaciones": [],
    "origen": "historico"
  },
  {
    "id": "lectura-0034",
    "sensorId": "sensor-002",
    "division": "Chuquicamata",
    "timestamp": "2025-08-01T12:30:28.000Z",
    "valor": 1284.27,
    "unidad": "kWh",
    "tipo": "energia_kwh",
    "participaEnCalculos": true,
    "anomalia": false,
    "motivos": [],
    "scoreAnomalia": 0,
    "valida": {
      "estado": "pendiente",
      "usuario": null,
      "comentario": null,
      "fecha": null
    },
    "historialValidaciones": [],
    "origen": "historico"
  },
  {
    "id": "lectura-0035",
    "sensorId": "sensor-002",
    "division": "Chuquicamata",
    "timestamp": "2025-08-01T12:40:16.000Z",
    "valor": 1269.466,
    "unidad": "kWh",
    "tipo": "energia_kwh",
    "participaEnCalculos": true,
    "anomalia": false,
    "motivos": [],
    "scoreAnomalia": 0,
    "valida": {
      "estado": "pendiente",
      "usuario": null,
      "comentario": null,
      "fecha": null
    },
    "historialValidaciones": [],
    "origen": "historico"
  },
  {
    "id": "lectura-0036",
    "sensorId": "sensor-002",
    "division": "Chuquicamata",
    "timestamp": "2025-08-01T12:50:47.000Z",
    "valor": 1362.5,
    "unidad": "kWh",
    "tipo": "energia_kwh",
    "participaEnCalculos": true,
    "anomalia": false,
    "motivos": [],
    "scoreAnomalia": 0,
    "valida": {
      "estado": "pendiente",
      "usuario": null,
      "comentario": null,
      "fecha": null
    },
    "historialValidaciones": [],
    "origen": "historico"
  },
  {
    "id": "lectura-0037",
    "sensorId": "sensor-002",
    "division": "Chuquicamata",
    "timestamp": "2025-08-01T13:00:16.000Z",
    "valor": 1286.672,
    "unidad": "kWh",
    "tipo": "energia_kwh",
    "participaEnCalculos": true,
    "anomalia": false,
    "motivos": [],
    "scoreAnomalia": 0,
    "valida": {
      "estado": "pendiente",
      "usuario": null,
      "comentario": null,
      "fecha": null
    },
    "historialValidaciones": [],
    "origen": "historico"
  },
  {
    "id": "lectura-0038",
    "sensorId": "sensor-002",
    "division": "Chuquicamata",
    "timestamp": "2025-08-01T13:10:31.000Z",
    "valor": 1262.826,
    "unidad": "kWh",
    "tipo": "energia_kwh",
    "participaEnCalculos": true,
    "anomalia": false,
    "motivos": [],
    "scoreAnomalia": 0,
    "valida": {
      "estado": "pendiente",
      "usuario": null,
      "comentario": null,
      "fecha": null
    },
    "historialValidaciones": [],
    "origen": "historico"
  },
  {
    "id": "lectura-0039",
    "sensorId": "sensor-002",
    "division": "Chuquicamata",
    "timestamp": "2025-08-01T13:20:19.000Z",
    "valor": 1276.634,
    "unidad": "kWh",
    "tipo": "energia_kwh",
    "participaEnCalculos": true,
    "anomalia": false,
    "motivos": [],
    "scoreAnomalia": 0,
    "valida": {
      "estado": "pendiente",
      "usuario": null,
      "comentario": null,
      "fecha": null
    },
    "historialValidaciones": [],
    "origen": "historico"
  },
  {
    "id": "lectura-0040",
    "sensorId": "sensor-002",
    "division": "Chuquicamata",
    "timestamp": "2025-08-01T13:30:23.000Z",
    "valor": 1267.342,
    "unidad": "kWh",
    "tipo": "energia_kwh",
    "participaEnCalculos": true,
    "anomalia": false,
    "motivos": [],
    "scoreAnomalia": 0,
    "valida": {
      "estado": "pendiente",
      "usuario": null,
      "comentario": null,
      "fecha": null
    },
    "historialValidaciones": [],
    "origen": "historico"
  },
  {
    "id": "lectura-0041",
    "sensorId": "sensor-002",
    "division": "Chuquicamata",
    "timestamp": "2025-08-01T13:40:31.000Z",
    "valor": 1275.279,
    "unidad": "kWh",
    "tipo": "energia_kwh",
    "participaEnCalculos": true,
    "anomalia": false,
    "motivos": [],
    "scoreAnomalia": 0,
    "valida": {
      "estado": "pendiente",
      "usuario": null,
      "comentario": null,
      "fecha": null
    },
    "historialValidaciones": [],
    "origen": "historico"
  },
  {
    "id": "lectura-0042",
    "sensorId": "sensor-002",
    "division": "Chuquicamata",
    "timestamp": "2025-08-01T13:50:12.000Z",
    "valor": 1284.308,
    "unidad": "kWh",
    "tipo": "energia_kwh",
    "participaEnCalculos": true,
    "anomalia": false,
    "motivos": [],
    "scoreAnomalia": 0,
    "valida": {
      "estado": "pendiente",
      "usuario": null,
      "comentario": null,
      "fecha": null
    },
    "historialValidaciones": [],
    "origen": "historico"
  },
  {
    "id": "lectura-0043",
    "sensorId": "sensor-002",
    "division": "Chuquicamata",
    "timestamp": "2025-08-01T14:00:22.000Z",
    "valor": 1175,
    "unidad": "kWh",
    "tipo": "energia_kwh",
    "participaEnCalculos": true,
    "anomalia": false,
    "motivos": [],
    "scoreAnomalia": 0,
    "valida": {
      "estado": "pendiente",
      "usuario": null,
      "comentario": null,
      "fecha": null
    },
    "historialValidaciones": [],
    "origen": "historico"
  },
  {
    "id": "lectura-0044",
    "sensorId": "sensor-002",
    "division": "Chuquicamata",
    "timestamp": "2025-08-01T14:10:43.000Z",
    "valor": 1281.007,
    "unidad": "kWh",
    "tipo": "energia_kwh",
    "participaEnCalculos": true,
    "anomalia": false,
    "motivos": [],
    "scoreAnomalia": 0,
    "valida": {
      "estado": "pendiente",
      "usuario": null,
      "comentario": null,
      "fecha": null
    },
    "historialValidaciones": [],
    "origen": "historico"
  },
  {
    "id": "lectura-0045",
    "sensorId": "sensor-002",
    "division": "Chuquicamata",
    "timestamp": "2025-08-01T14:20:45.000Z",
    "valor": 1274.499,
    "unidad": "kWh",
    "tipo": "energia_kwh",
    "participaEnCalculos": true,
    "anomalia": false,
    "motivos": [],
    "scoreAnomalia": 0,
    "valida": {
      "estado": "pendiente",
      "usuario": null,
      "comentario": null,
      "fecha": null
    },
    "historialValidaciones": [],
    "origen": "historico"
  },
  {
    "id": "lectura-0046",
    "sensorId": "sensor-002",
    "division": "Chuquicamata",
    "timestamp": "2025-08-01T14:30:09.000Z",
    "valor": 1268.785,
    "unidad": "kWh",
    "tipo": "energia_kwh",
    "participaEnCalculos": true,
    "anomalia": false,
    "motivos": [],
    "scoreAnomalia": 0,
    "valida": {
      "estado": "pendiente",
      "usuario": null,
      "comentario": null,
      "fecha": null
    },
    "historialValidaciones": [],
    "origen": "historico"
  },
  {
    "id": "lectura-0047",
    "sensorId": "sensor-002",
    "division": "Chuquicamata",
    "timestamp": "2025-08-01T14:40:23.000Z",
    "valor": 1270.703,
    "unidad": "kWh",
    "tipo": "energia_kwh",
    "participaEnCalculos": true,
    "anomalia": false,
    "motivos": [],
    "scoreAnomalia": 0,
    "valida": {
      "estado": "pendiente",
      "usuario": null,
      "comentario": null,
      "fecha": null
    },
    "historialValidaciones": [],
    "origen": "historico"
  },
  {
    "id": "lectura-0048",
    "sensorId": "sensor-002",
    "division": "Chuquicamata",
    "timestamp": "2025-08-01T14:50:29.000Z",
    "valor": 1282.167,
    "unidad": "kWh",
    "tipo": "energia_kwh",
    "participaEnCalculos": true,
    "anomalia": false,
    "motivos": [],
    "scoreAnomalia": 0,
    "valida": {
      "estado": "pendiente",
      "usuario": null,
      "comentario": null,
      "fecha": null
    },
    "historialValidaciones": [],
    "origen": "historico"
  },
  {
    "id": "lectura-0049",
    "sensorId": "sensor-002",
    "division": "Chuquicamata",
    "timestamp": "2025-08-01T15:00:39.000Z",
    "valor": 1290,
    "unidad": "kWh",
    "tipo": "energia_kwh",
    "participaEnCalculos": true,
    "anomalia": false,
    "motivos": [],
    "scoreAnomalia": 0,
    "valida": {
      "estado": "pendiente",
      "usuario": null,
      "comentario": null,
      "fecha": null
    },
    "historialValidaciones": [],
    "origen": "historico"
  },
  {
    "id": "lectura-0050",
    "sensorId": "sensor-002",
    "division": "Chuquicamata",
    "timestamp": "2025-08-01T15:10:45.000Z",
    "valor": 1274.338,
    "unidad": "kWh",
    "tipo": "energia_kwh",
    "participaEnCalculos": true,
    "anomalia": false,
    "motivos": [],
    "scoreAnomalia": 0,
    "valida": {
      "estado": "pendiente",
      "usuario": null,
      "comentario": null,
      "fecha": null
    },
    "historialValidaciones": [],
    "origen": "historico"
  },
  {
    "id": "lectura-0051",
    "sensorId": "sensor-002",
    "division": "Chuquicamata",
    "timestamp": "2025-08-01T15:20:16.000Z",
    "valor": 1266.119,
    "unidad": "kWh",
    "tipo": "energia_kwh",
    "participaEnCalculos": true,
    "anomalia": false,
    "motivos": [],
    "scoreAnomalia": 0,
    "valida": {
      "estado": "pendiente",
      "usuario": null,
      "comentario": null,
      "fecha": null
    },
    "historialValidaciones": [],
    "origen": "historico"
  },
  {
    "id": "lectura-0052",
    "sensorId": "sensor-002",
    "division": "Chuquicamata",
    "timestamp": "2025-08-01T15:30:23.000Z",
    "valor": 1286.764,
    "unidad": "kWh",
    "tipo": "energia_kwh",
    "participaEnCalculos": true,
    "anomalia": false,
    "motivos": [],
    "scoreAnomalia": 0,
    "valida": {
      "estado": "pendiente",
      "usuario": null,
      "comentario": null,
      "fecha": null
    },
    "historialValidaciones": [],
    "origen": "historico"
  },
  {
    "id": "lectura-0053",
    "sensorId": "sensor-002",
    "division": "Chuquicamata",
    "timestamp": "2025-08-01T15:40:22.000Z",
    "valor": 1400,
    "unidad": "kWh",
    "tipo": "energia_kwh",
    "participaEnCalculos": true,
    "anomalia": false,
    "motivos": [],
    "scoreAnomalia": 0,
    "valida": {
      "estado": "pendiente",
      "usuario": null,
      "comentario": null,
      "fecha": null
    },
    "historialValidaciones": [],
    "origen": "historico"
  },
  {
    "id": "lectura-0054",
    "sensorId": "sensor-002",
    "division": "Chuquicamata",
    "timestamp": "2025-08-01T15:50:17.000Z",
    "valor": 1269.964,
    "unidad": "kWh",
    "tipo": "energia_kwh",
    "participaEnCalculos": true,
    "anomalia": false,
    "motivos": [],
    "scoreAnomalia": 0,
    "valida": {
      "estado": "pendiente",
      "usuario": null,
      "comentario": null,
      "fecha": null
    },
    "historialValidaciones": [],
    "origen": "historico"
  },
  {
    "id": "lectura-0055",
    "sensorId": "sensor-002",
    "division": "Chuquicamata",
    "timestamp": "2025-08-01T16:00:12.000Z",
    "valor": 1272.145,
    "unidad": "kWh",
    "tipo": "energia_kwh",
    "participaEnCalculos": true,
    "anomalia": false,
    "motivos": [],
    "scoreAnomalia": 0,
    "valida": {
      "estado": "pendiente",
      "usuario": null,
      "comentario": null,
      "fecha": null
    },
    "historialValidaciones": [],
    "origen": "historico"
  },
  {
    "id": "lectura-0056",
    "sensorId": "sensor-002",
    "division": "Chuquicamata",
    "timestamp": "2025-08-01T16:10:29.000Z",
    "valor": 1277.676,
    "unidad": "kWh",
    "tipo": "energia_kwh",
    "participaEnCalculos": true,
    "anomalia": false,
    "motivos": [],
    "scoreAnomalia": 0,
    "valida": {
      "estado": "pendiente",
      "usuario": null,
      "comentario": null,
      "fecha": null
    },
    "historialValidaciones": [],
    "origen": "historico"
  },
  {
    "id": "lectura-0057",
    "sensorId": "sensor-002",
    "division": "Chuquicamata",
    "timestamp": "2025-08-01T16:20:39.000Z",
    "valor": 1282.299,
    "unidad": "kWh",
    "tipo": "energia_kwh",
    "participaEnCalculos": true,
    "anomalia": false,
    "motivos": [],
    "scoreAnomalia": 0,
    "valida": {
      "estado": "pendiente",
      "usuario": null,
      "comentario": null,
      "fecha": null
    },
    "historialValidaciones": [],
    "origen": "historico"
  },
  {
    "id": "lectura-0058",
    "sensorId": "sensor-002",
    "division": "Chuquicamata",
    "timestamp": "2025-08-01T16:30:48.000Z",
    "valor": 1150,
    "unidad": "kWh",
    "tipo": "energia_kwh",
    "participaEnCalculos": true,
    "anomalia": false,
    "motivos": [],
    "scoreAnomalia": 0,
    "valida": {
      "estado": "pendiente",
      "usuario": null,
      "comentario": null,
      "fecha": null
    },
    "historialValidaciones": [],
    "origen": "historico"
  },
  {
    "id": "lectura-0059",
    "sensorId": "sensor-002",
    "division": "Chuquicamata",
    "timestamp": "2025-08-01T16:40:15.000Z",
    "valor": 1268.48,
    "unidad": "kWh",
    "tipo": "energia_kwh",
    "participaEnCalculos": true,
    "anomalia": false,
    "motivos": [],
    "scoreAnomalia": 0,
    "valida": {
      "estado": "pendiente",
      "usuario": null,
      "comentario": null,
      "fecha": null
    },
    "historialValidaciones": [],
    "origen": "historico"
  },
  {
    "id": "lectura-0060",
    "sensorId": "sensor-002",
    "division": "Chuquicamata",
    "timestamp": "2025-08-01T16:50:11.000Z",
    "valor": 1282.966,
    "unidad": "kWh",
    "tipo": "energia_kwh",
    "participaEnCalculos": true,
    "anomalia": false,
    "motivos": [],
    "scoreAnomalia": 0,
    "valida": {
      "estado": "pendiente",
      "usuario": null,
      "comentario": null,
      "fecha": null
    },
    "historialValidaciones": [],
    "origen": "historico"
  },
  {
    "id": "lectura-0061",
    "sensorId": "sensor-003",
    "division": "División Andina",
    "timestamp": "2025-08-01T12:00:28.000Z",
    "valor": 1187.295,
    "unidad": "°C",
    "tipo": "temperatura_c",
    "participaEnCalculos": true,
    "anomalia": false,
    "motivos": [],
    "scoreAnomalia": 0,
    "valida": {
      "estado": "pendiente",
      "usuario": null,
      "comentario": null,
      "fecha": null
    },
    "historialValidaciones": [],
    "origen": "historico"
  },
  {
    "id": "lectura-0062",
    "sensorId": "sensor-003",
    "division": "División Andina",
    "timestamp": "2025-08-01T12:03:19.000Z",
    "valor": 1184.664,
    "unidad": "°C",
    "tipo": "temperatura_c",
    "participaEnCalculos": true,
    "anomalia": false,
    "motivos": [],
    "scoreAnomalia": 0,
    "valida": {
      "estado": "pendiente",
      "usuario": null,
      "comentario": null,
      "fecha": null
    },
    "historialValidaciones": [],
    "origen": "historico"
  },
  {
    "id": "lectura-0063",
    "sensorId": "sensor-003",
    "division": "División Andina",
    "timestamp": "2025-08-01T12:06:05.000Z",
    "valor": 1188.348,
    "unidad": "°C",
    "tipo": "temperatura_c",
    "participaEnCalculos": true,
    "anomalia": false,
    "motivos": [],
    "scoreAnomalia": 0,
    "valida": {
      "estado": "pendiente",
      "usuario": null,
      "comentario": null,
      "fecha": null
    },
    "historialValidaciones": [],
    "origen": "historico"
  },
  {
    "id": "lectura-0064",
    "sensorId": "sensor-003",
    "division": "División Andina",
    "timestamp": "2025-08-01T12:09:01.000Z",
    "valor": 1181.494,
    "unidad": "°C",
    "tipo": "temperatura_c",
    "participaEnCalculos": true,
    "anomalia": false,
    "motivos": [],
    "scoreAnomalia": 0,
    "valida": {
      "estado": "pendiente",
      "usuario": null,
      "comentario": null,
      "fecha": null
    },
    "historialValidaciones": [],
    "origen": "historico"
  },
  {
    "id": "lectura-0065",
    "sensorId": "sensor-003",
    "division": "División Andina",
    "timestamp": "2025-08-01T12:12:17.000Z",
    "valor": 1181.31,
    "unidad": "°C",
    "tipo": "temperatura_c",
    "participaEnCalculos": true,
    "anomalia": false,
    "motivos": [],
    "scoreAnomalia": 0,
    "valida": {
      "estado": "pendiente",
      "usuario": null,
      "comentario": null,
      "fecha": null
    },
    "historialValidaciones": [],
    "origen": "historico"
  },
  {
    "id": "lectura-0066",
    "sensorId": "sensor-003",
    "division": "División Andina",
    "timestamp": "2025-08-01T12:15:10.000Z",
    "valor": 1213,
    "unidad": "°C",
    "tipo": "temperatura_c",
    "participaEnCalculos": true,
    "anomalia": false,
    "motivos": [],
    "scoreAnomalia": 0,
    "valida": {
      "estado": "pendiente",
      "usuario": null,
      "comentario": null,
      "fecha": null
    },
    "historialValidaciones": [],
    "origen": "historico"
  },
  {
    "id": "lectura-0067",
    "sensorId": "sensor-003",
    "division": "División Andina",
    "timestamp": "2025-08-01T12:18:33.000Z",
    "valor": 1181.335,
    "unidad": "°C",
    "tipo": "temperatura_c",
    "participaEnCalculos": true,
    "anomalia": false,
    "motivos": [],
    "scoreAnomalia": 0,
    "valida": {
      "estado": "pendiente",
      "usuario": null,
      "comentario": null,
      "fecha": null
    },
    "historialValidaciones": [],
    "origen": "historico"
  },
  {
    "id": "lectura-0068",
    "sensorId": "sensor-003",
    "division": "División Andina",
    "timestamp": "2025-08-01T12:21:26.000Z",
    "valor": 1183.297,
    "unidad": "°C",
    "tipo": "temperatura_c",
    "participaEnCalculos": true,
    "anomalia": false,
    "motivos": [],
    "scoreAnomalia": 0,
    "valida": {
      "estado": "pendiente",
      "usuario": null,
      "comentario": null,
      "fecha": null
    },
    "historialValidaciones": [],
    "origen": "historico"
  },
  {
    "id": "lectura-0069",
    "sensorId": "sensor-003",
    "division": "División Andina",
    "timestamp": "2025-08-01T12:24:30.000Z",
    "valor": 1185.251,
    "unidad": "°C",
    "tipo": "temperatura_c",
    "participaEnCalculos": true,
    "anomalia": false,
    "motivos": [],
    "scoreAnomalia": 0,
    "valida": {
      "estado": "pendiente",
      "usuario": null,
      "comentario": null,
      "fecha": null
    },
    "historialValidaciones": [],
    "origen": "historico"
  },
  {
    "id": "lectura-0070",
    "sensorId": "sensor-003",
    "division": "División Andina",
    "timestamp": "2025-08-01T12:27:06.000Z",
    "valor": 1181.09,
    "unidad": "°C",
    "tipo": "temperatura_c",
    "participaEnCalculos": true,
    "anomalia": false,
    "motivos": [],
    "scoreAnomalia": 0,
    "valida": {
      "estado": "pendiente",
      "usuario": null,
      "comentario": null,
      "fecha": null
    },
    "historialValidaciones": [],
    "origen": "historico"
  },
  {
    "id": "lectura-0071",
    "sensorId": "sensor-003",
    "division": "División Andina",
    "timestamp": "2025-08-01T12:30:16.000Z",
    "valor": 1183.863,
    "unidad": "°C",
    "tipo": "temperatura_c",
    "participaEnCalculos": true,
    "anomalia": false,
    "motivos": [],
    "scoreAnomalia": 0,
    "valida": {
      "estado": "pendiente",
      "usuario": null,
      "comentario": null,
      "fecha": null
    },
    "historialValidaciones": [],
    "origen": "historico"
  },
  {
    "id": "lectura-0072",
    "sensorId": "sensor-003",
    "division": "División Andina",
    "timestamp": "2025-08-01T12:33:42.000Z",
    "valor": 1188.455,
    "unidad": "°C",
    "tipo": "temperatura_c",
    "participaEnCalculos": true,
    "anomalia": false,
    "motivos": [],
    "scoreAnomalia": 0,
    "valida": {
      "estado": "pendiente",
      "usuario": null,
      "comentario": null,
      "fecha": null
    },
    "historialValidaciones": [],
    "origen": "historico"
  },
  {
    "id": "lectura-0073",
    "sensorId": "sensor-003",
    "division": "División Andina",
    "timestamp": "2025-08-01T12:36:35.000Z",
    "valor": 1153,
    "unidad": "°C",
    "tipo": "temperatura_c",
    "participaEnCalculos": true,
    "anomalia": false,
    "motivos": [],
    "scoreAnomalia": 0,
    "valida": {
      "estado": "pendiente",
      "usuario": null,
      "comentario": null,
      "fecha": null
    },
    "historialValidaciones": [],
    "origen": "historico"
  },
  {
    "id": "lectura-0074",
    "sensorId": "sensor-003",
    "division": "División Andina",
    "timestamp": "2025-08-01T12:39:33.000Z",
    "valor": 1188.303,
    "unidad": "°C",
    "tipo": "temperatura_c",
    "participaEnCalculos": true,
    "anomalia": false,
    "motivos": [],
    "scoreAnomalia": 0,
    "valida": {
      "estado": "pendiente",
      "usuario": null,
      "comentario": null,
      "fecha": null
    },
    "historialValidaciones": [],
    "origen": "historico"
  },
  {
    "id": "lectura-0075",
    "sensorId": "sensor-003",
    "division": "División Andina",
    "timestamp": "2025-08-01T12:42:30.000Z",
    "valor": 1187.275,
    "unidad": "°C",
    "tipo": "temperatura_c",
    "participaEnCalculos": true,
    "anomalia": false,
    "motivos": [],
    "scoreAnomalia": 0,
    "valida": {
      "estado": "pendiente",
      "usuario": null,
      "comentario": null,
      "fecha": null
    },
    "historialValidaciones": [],
    "origen": "historico"
  },
  {
    "id": "lectura-0076",
    "sensorId": "sensor-003",
    "division": "División Andina",
    "timestamp": "2025-08-01T12:45:22.000Z",
    "valor": 1181.738,
    "unidad": "°C",
    "tipo": "temperatura_c",
    "participaEnCalculos": true,
    "anomalia": false,
    "motivos": [],
    "scoreAnomalia": 0,
    "valida": {
      "estado": "pendiente",
      "usuario": null,
      "comentario": null,
      "fecha": null
    },
    "historialValidaciones": [],
    "origen": "historico"
  },
  {
    "id": "lectura-0077",
    "sensorId": "sensor-003",
    "division": "División Andina",
    "timestamp": "2025-08-01T12:48:48.000Z",
    "valor": 1185.153,
    "unidad": "°C",
    "tipo": "temperatura_c",
    "participaEnCalculos": true,
    "anomalia": false,
    "motivos": [],
    "scoreAnomalia": 0,
    "valida": {
      "estado": "pendiente",
      "usuario": null,
      "comentario": null,
      "fecha": null
    },
    "historialValidaciones": [],
    "origen": "historico"
  },
  {
    "id": "lectura-0078",
    "sensorId": "sensor-003",
    "division": "División Andina",
    "timestamp": "2025-08-01T12:51:22.000Z",
    "valor": 1184.675,
    "unidad": "°C",
    "tipo": "temperatura_c",
    "participaEnCalculos": true,
    "anomalia": false,
    "motivos": [],
    "scoreAnomalia": 0,
    "valida": {
      "estado": "pendiente",
      "usuario": null,
      "comentario": null,
      "fecha": null
    },
    "historialValidaciones": [],
    "origen": "historico"
  },
  {
    "id": "lectura-0079",
    "sensorId": "sensor-003",
    "division": "División Andina",
    "timestamp": "2025-08-01T12:54:05.000Z",
    "valor": 1189.8,
    "unidad": "°C",
    "tipo": "temperatura_c",
    "participaEnCalculos": true,
    "anomalia": false,
    "motivos": [],
    "scoreAnomalia": 0,
    "valida": {
      "estado": "pendiente",
      "usuario": null,
      "comentario": null,
      "fecha": null
    },
    "historialValidaciones": [],
    "origen": "historico"
  },
  {
    "id": "lectura-0080",
    "sensorId": "sensor-003",
    "division": "División Andina",
    "timestamp": "2025-08-01T12:57:17.000Z",
    "valor": 1185.574,
    "unidad": "°C",
    "tipo": "temperatura_c",
    "participaEnCalculos": true,
    "anomalia": false,
    "motivos": [],
    "scoreAnomalia": 0,
    "valida": {
      "estado": "pendiente",
      "usuario": null,
      "comentario": null,
      "fecha": null
    },
    "historialValidaciones": [],
    "origen": "historico"
  },
  {
    "id": "lectura-0081",
    "sensorId": "sensor-003",
    "division": "División Andina",
    "timestamp": "2025-08-01T13:00:39.000Z",
    "valor": 1184.177,
    "unidad": "°C",
    "tipo": "temperatura_c",
    "participaEnCalculos": true,
    "anomalia": false,
    "motivos": [],
    "scoreAnomalia": 0,
    "valida": {
      "estado": "pendiente",
      "usuario": null,
      "comentario": null,
      "fecha": null
    },
    "historialValidaciones": [],
    "origen": "historico"
  },
  {
    "id": "lectura-0082",
    "sensorId": "sensor-003",
    "division": "División Andina",
    "timestamp": "2025-08-01T13:03:01.000Z",
    "valor": 1181.284,
    "unidad": "°C",
    "tipo": "temperatura_c",
    "participaEnCalculos": true,
    "anomalia": false,
    "motivos": [],
    "scoreAnomalia": 0,
    "valida": {
      "estado": "pendiente",
      "usuario": null,
      "comentario": null,
      "fecha": null
    },
    "historialValidaciones": [],
    "origen": "historico"
  },
  {
    "id": "lectura-0083",
    "sensorId": "sensor-003",
    "division": "División Andina",
    "timestamp": "2025-08-01T13:06:26.000Z",
    "valor": 1225,
    "unidad": "°C",
    "tipo": "temperatura_c",
    "participaEnCalculos": true,
    "anomalia": false,
    "motivos": [],
    "scoreAnomalia": 0,
    "valida": {
      "estado": "pendiente",
      "usuario": null,
      "comentario": null,
      "fecha": null
    },
    "historialValidaciones": [],
    "origen": "historico"
  },
  {
    "id": "lectura-0084",
    "sensorId": "sensor-003",
    "division": "División Andina",
    "timestamp": "2025-08-01T13:09:06.000Z",
    "valor": 1181.614,
    "unidad": "°C",
    "tipo": "temperatura_c",
    "participaEnCalculos": true,
    "anomalia": false,
    "motivos": [],
    "scoreAnomalia": 0,
    "valida": {
      "estado": "pendiente",
      "usuario": null,
      "comentario": null,
      "fecha": null
    },
    "historialValidaciones": [],
    "origen": "historico"
  },
  {
    "id": "lectura-0085",
    "sensorId": "sensor-003",
    "division": "División Andina",
    "timestamp": "2025-08-01T13:12:42.000Z",
    "valor": 1186.303,
    "unidad": "°C",
    "tipo": "temperatura_c",
    "participaEnCalculos": true,
    "anomalia": false,
    "motivos": [],
    "scoreAnomalia": 0,
    "valida": {
      "estado": "pendiente",
      "usuario": null,
      "comentario": null,
      "fecha": null
    },
    "historialValidaciones": [],
    "origen": "historico"
  },
  {
    "id": "lectura-0086",
    "sensorId": "sensor-003",
    "division": "División Andina",
    "timestamp": "2025-08-01T13:15:43.000Z",
    "valor": 1187.339,
    "unidad": "°C",
    "tipo": "temperatura_c",
    "participaEnCalculos": true,
    "anomalia": false,
    "motivos": [],
    "scoreAnomalia": 0,
    "valida": {
      "estado": "pendiente",
      "usuario": null,
      "comentario": null,
      "fecha": null
    },
    "historialValidaciones": [],
    "origen": "historico"
  },
  {
    "id": "lectura-0087",
    "sensorId": "sensor-003",
    "division": "División Andina",
    "timestamp": "2025-08-01T13:18:08.000Z",
    "valor": 1187.374,
    "unidad": "°C",
    "tipo": "temperatura_c",
    "participaEnCalculos": true,
    "anomalia": false,
    "motivos": [],
    "scoreAnomalia": 0,
    "valida": {
      "estado": "pendiente",
      "usuario": null,
      "comentario": null,
      "fecha": null
    },
    "historialValidaciones": [],
    "origen": "historico"
  },
  {
    "id": "lectura-0088",
    "sensorId": "sensor-003",
    "division": "División Andina",
    "timestamp": "2025-08-01T13:21:40.000Z",
    "valor": 1145,
    "unidad": "°C",
    "tipo": "temperatura_c",
    "participaEnCalculos": true,
    "anomalia": false,
    "motivos": [],
    "scoreAnomalia": 0,
    "valida": {
      "estado": "pendiente",
      "usuario": null,
      "comentario": null,
      "fecha": null
    },
    "historialValidaciones": [],
    "origen": "historico"
  },
  {
    "id": "lectura-0089",
    "sensorId": "sensor-003",
    "division": "División Andina",
    "timestamp": "2025-08-01T13:24:17.000Z",
    "valor": 1183.959,
    "unidad": "°C",
    "tipo": "temperatura_c",
    "participaEnCalculos": true,
    "anomalia": false,
    "motivos": [],
    "scoreAnomalia": 0,
    "valida": {
      "estado": "pendiente",
      "usuario": null,
      "comentario": null,
      "fecha": null
    },
    "historialValidaciones": [],
    "origen": "historico"
  },
  {
    "id": "lectura-0090",
    "sensorId": "sensor-003",
    "division": "División Andina",
    "timestamp": "2025-08-01T13:27:25.000Z",
    "valor": 1188.971,
    "unidad": "°C",
    "tipo": "temperatura_c",
    "participaEnCalculos": true,
    "anomalia": false,
    "motivos": [],
    "scoreAnomalia": 0,
    "valida": {
      "estado": "pendiente",
      "usuario": null,
      "comentario": null,
      "fecha": null
    },
    "historialValidaciones": [],
    "origen": "historico"
  },
  {
    "id": "lectura-0091",
    "sensorId": "sensor-004",
    "division": "Radomiro Tomic",
    "timestamp": "2025-08-01T12:00:11.000Z",
    "valor": 420.628,
    "unidad": "m3/h",
    "tipo": "caudal_m3_h",
    "participaEnCalculos": true,
    "anomalia": false,
    "motivos": [],
    "scoreAnomalia": 0,
    "valida": {
      "estado": "pendiente",
      "usuario": null,
      "comentario": null,
      "fecha": null
    },
    "historialValidaciones": [],
    "origen": "historico"
  },
  {
    "id": "lectura-0092",
    "sensorId": "sensor-004",
    "division": "Radomiro Tomic",
    "timestamp": "2025-08-01T12:04:02.000Z",
    "valor": 421.448,
    "unidad": "m3/h",
    "tipo": "caudal_m3_h",
    "participaEnCalculos": true,
    "anomalia": false,
    "motivos": [],
    "scoreAnomalia": 0,
    "valida": {
      "estado": "pendiente",
      "usuario": null,
      "comentario": null,
      "fecha": null
    },
    "historialValidaciones": [],
    "origen": "historico"
  },
  {
    "id": "lectura-0093",
    "sensorId": "sensor-004",
    "division": "Radomiro Tomic",
    "timestamp": "2025-08-01T12:08:15.000Z",
    "valor": 425.771,
    "unidad": "m3/h",
    "tipo": "caudal_m3_h",
    "participaEnCalculos": true,
    "anomalia": false,
    "motivos": [],
    "scoreAnomalia": 0,
    "valida": {
      "estado": "pendiente",
      "usuario": null,
      "comentario": null,
      "fecha": null
    },
    "historialValidaciones": [],
    "origen": "historico"
  },
  {
    "id": "lectura-0094",
    "sensorId": "sensor-004",
    "division": "Radomiro Tomic",
    "timestamp": "2025-08-01T12:12:47.000Z",
    "valor": 422.296,
    "unidad": "m3/h",
    "tipo": "caudal_m3_h",
    "participaEnCalculos": true,
    "anomalia": false,
    "motivos": [],
    "scoreAnomalia": 0,
    "valida": {
      "estado": "pendiente",
      "usuario": null,
      "comentario": null,
      "fecha": null
    },
    "historialValidaciones": [],
    "origen": "historico"
  },
  {
    "id": "lectura-0095",
    "sensorId": "sensor-004",
    "division": "Radomiro Tomic",
    "timestamp": "2025-08-01T12:16:18.000Z",
    "valor": 425.508,
    "unidad": "m3/h",
    "tipo": "caudal_m3_h",
    "participaEnCalculos": true,
    "anomalia": false,
    "motivos": [],
    "scoreAnomalia": 0,
    "valida": {
      "estado": "pendiente",
      "usuario": null,
      "comentario": null,
      "fecha": null
    },
    "historialValidaciones": [],
    "origen": "historico"
  },
  {
    "id": "lectura-0096",
    "sensorId": "sensor-004",
    "division": "Radomiro Tomic",
    "timestamp": "2025-08-01T12:20:19.000Z",
    "valor": 467,
    "unidad": "m3/h",
    "tipo": "caudal_m3_h",
    "participaEnCalculos": true,
    "anomalia": false,
    "motivos": [],
    "scoreAnomalia": 0,
    "valida": {
      "estado": "pendiente",
      "usuario": null,
      "comentario": null,
      "fecha": null
    },
    "historialValidaciones": [],
    "origen": "historico"
  },
  {
    "id": "lectura-0097",
    "sensorId": "sensor-004",
    "division": "Radomiro Tomic",
    "timestamp": "2025-08-01T12:24:00.000Z",
    "valor": 423.857,
    "unidad": "m3/h",
    "tipo": "caudal_m3_h",
    "participaEnCalculos": true,
    "anomalia": false,
    "motivos": [],
    "scoreAnomalia": 0,
    "valida": {
      "estado": "pendiente",
      "usuario": null,
      "comentario": null,
      "fecha": null
    },
    "historialValidaciones": [],
    "origen": "historico"
  },
  {
    "id": "lectura-0098",
    "sensorId": "sensor-004",
    "division": "Radomiro Tomic",
    "timestamp": "2025-08-01T12:28:08.000Z",
    "valor": 421.672,
    "unidad": "m3/h",
    "tipo": "caudal_m3_h",
    "participaEnCalculos": true,
    "anomalia": false,
    "motivos": [],
    "scoreAnomalia": 0,
    "valida": {
      "estado": "pendiente",
      "usuario": null,
      "comentario": null,
      "fecha": null
    },
    "historialValidaciones": [],
    "origen": "historico"
  },
  {
    "id": "lectura-0099",
    "sensorId": "sensor-004",
    "division": "Radomiro Tomic",
    "timestamp": "2025-08-01T12:32:21.000Z",
    "valor": 420.55,
    "unidad": "m3/h",
    "tipo": "caudal_m3_h",
    "participaEnCalculos": true,
    "anomalia": false,
    "motivos": [],
    "scoreAnomalia": 0,
    "valida": {
      "estado": "pendiente",
      "usuario": null,
      "comentario": null,
      "fecha": null
    },
    "historialValidaciones": [],
    "origen": "historico"
  },
  {
    "id": "lectura-0100",
    "sensorId": "sensor-004",
    "division": "Radomiro Tomic",
    "timestamp": "2025-08-01T12:36:03.000Z",
    "valor": 430.929,
    "unidad": "m3/h",
    "tipo": "caudal_m3_h",
    "participaEnCalculos": true,
    "anomalia": false,
    "motivos": [],
    "scoreAnomalia": 0,
    "valida": {
      "estado": "pendiente",
      "usuario": null,
      "comentario": null,
      "fecha": null
    },
    "historialValidaciones": [],
    "origen": "historico"
  },
  {
    "id": "lectura-0101",
    "sensorId": "sensor-004",
    "division": "Radomiro Tomic",
    "timestamp": "2025-08-01T12:40:10.000Z",
    "valor": 423.391,
    "unidad": "m3/h",
    "tipo": "caudal_m3_h",
    "participaEnCalculos": true,
    "anomalia": false,
    "motivos": [],
    "scoreAnomalia": 0,
    "valida": {
      "estado": "pendiente",
      "usuario": null,
      "comentario": null,
      "fecha": null
    },
    "historialValidaciones": [],
    "origen": "historico"
  },
  {
    "id": "lectura-0102",
    "sensorId": "sensor-004",
    "division": "Radomiro Tomic",
    "timestamp": "2025-08-01T12:44:42.000Z",
    "valor": 428.085,
    "unidad": "m3/h",
    "tipo": "caudal_m3_h",
    "participaEnCalculos": true,
    "anomalia": false,
    "motivos": [],
    "scoreAnomalia": 0,
    "valida": {
      "estado": "pendiente",
      "usuario": null,
      "comentario": null,
      "fecha": null
    },
    "historialValidaciones": [],
    "origen": "historico"
  },
  {
    "id": "lectura-0103",
    "sensorId": "sensor-004",
    "division": "Radomiro Tomic",
    "timestamp": "2025-08-01T12:48:10.000Z",
    "valor": 377,
    "unidad": "m3/h",
    "tipo": "caudal_m3_h",
    "participaEnCalculos": true,
    "anomalia": false,
    "motivos": [],
    "scoreAnomalia": 0,
    "valida": {
      "estado": "pendiente",
      "usuario": null,
      "comentario": null,
      "fecha": null
    },
    "historialValidaciones": [],
    "origen": "historico"
  },
  {
    "id": "lectura-0104",
    "sensorId": "sensor-004",
    "division": "Radomiro Tomic",
    "timestamp": "2025-08-01T12:52:46.000Z",
    "valor": 429.001,
    "unidad": "m3/h",
    "tipo": "caudal_m3_h",
    "participaEnCalculos": true,
    "anomalia": false,
    "motivos": [],
    "scoreAnomalia": 0,
    "valida": {
      "estado": "pendiente",
      "usuario": null,
      "comentario": null,
      "fecha": null
    },
    "historialValidaciones": [],
    "origen": "historico"
  },
  {
    "id": "lectura-0105",
    "sensorId": "sensor-004",
    "division": "Radomiro Tomic",
    "timestamp": "2025-08-01T12:56:27.000Z",
    "valor": 428.494,
    "unidad": "m3/h",
    "tipo": "caudal_m3_h",
    "participaEnCalculos": true,
    "anomalia": false,
    "motivos": [],
    "scoreAnomalia": 0,
    "valida": {
      "estado": "pendiente",
      "usuario": null,
      "comentario": null,
      "fecha": null
    },
    "historialValidaciones": [],
    "origen": "historico"
  },
  {
    "id": "lectura-0106",
    "sensorId": "sensor-004",
    "division": "Radomiro Tomic",
    "timestamp": "2025-08-01T13:00:30.000Z",
    "valor": 423.164,
    "unidad": "m3/h",
    "tipo": "caudal_m3_h",
    "participaEnCalculos": true,
    "anomalia": false,
    "motivos": [],
    "scoreAnomalia": 0,
    "valida": {
      "estado": "pendiente",
      "usuario": null,
      "comentario": null,
      "fecha": null
    },
    "historialValidaciones": [],
    "origen": "historico"
  },
  {
    "id": "lectura-0107",
    "sensorId": "sensor-004",
    "division": "Radomiro Tomic",
    "timestamp": "2025-08-01T13:04:21.000Z",
    "valor": 420.118,
    "unidad": "m3/h",
    "tipo": "caudal_m3_h",
    "participaEnCalculos": true,
    "anomalia": false,
    "motivos": [],
    "scoreAnomalia": 0,
    "valida": {
      "estado": "pendiente",
      "usuario": null,
      "comentario": null,
      "fecha": null
    },
    "historialValidaciones": [],
    "origen": "historico"
  },
  {
    "id": "lectura-0108",
    "sensorId": "sensor-004",
    "division": "Radomiro Tomic",
    "timestamp": "2025-08-01T13:08:25.000Z",
    "valor": 427.043,
    "unidad": "m3/h",
    "tipo": "caudal_m3_h",
    "participaEnCalculos": true,
    "anomalia": false,
    "motivos": [],
    "scoreAnomalia": 0,
    "valida": {
      "estado": "pendiente",
      "usuario": null,
      "comentario": null,
      "fecha": null
    },
    "historialValidaciones": [],
    "origen": "historico"
  },
  {
    "id": "lectura-0109",
    "sensorId": "sensor-004",
    "division": "Radomiro Tomic",
    "timestamp": "2025-08-01T13:12:46.000Z",
    "valor": 432.2,
    "unidad": "m3/h",
    "tipo": "caudal_m3_h",
    "participaEnCalculos": true,
    "anomalia": false,
    "motivos": [],
    "scoreAnomalia": 0,
    "valida": {
      "estado": "pendiente",
      "usuario": null,
      "comentario": null,
      "fecha": null
    },
    "historialValidaciones": [],
    "origen": "historico"
  },
  {
    "id": "lectura-0110",
    "sensorId": "sensor-004",
    "division": "Radomiro Tomic",
    "timestamp": "2025-08-01T13:16:26.000Z",
    "valor": 425.939,
    "unidad": "m3/h",
    "tipo": "caudal_m3_h",
    "participaEnCalculos": true,
    "anomalia": false,
    "motivos": [],
    "scoreAnomalia": 0,
    "valida": {
      "estado": "pendiente",
      "usuario": null,
      "comentario": null,
      "fecha": null
    },
    "historialValidaciones": [],
    "origen": "historico"
  },
  {
    "id": "lectura-0111",
    "sensorId": "sensor-004",
    "division": "Radomiro Tomic",
    "timestamp": "2025-08-01T13:20:43.000Z",
    "valor": 421.98,
    "unidad": "m3/h",
    "tipo": "caudal_m3_h",
    "participaEnCalculos": true,
    "anomalia": false,
    "motivos": [],
    "scoreAnomalia": 0,
    "valida": {
      "estado": "pendiente",
      "usuario": null,
      "comentario": null,
      "fecha": null
    },
    "historialValidaciones": [],
    "origen": "historico"
  },
  {
    "id": "lectura-0112",
    "sensorId": "sensor-004",
    "division": "Radomiro Tomic",
    "timestamp": "2025-08-01T13:24:07.000Z",
    "valor": 422.112,
    "unidad": "m3/h",
    "tipo": "caudal_m3_h",
    "participaEnCalculos": true,
    "anomalia": false,
    "motivos": [],
    "scoreAnomalia": 0,
    "valida": {
      "estado": "pendiente",
      "usuario": null,
      "comentario": null,
      "fecha": null
    },
    "historialValidaciones": [],
    "origen": "historico"
  },
  {
    "id": "lectura-0113",
    "sensorId": "sensor-004",
    "division": "Radomiro Tomic",
    "timestamp": "2025-08-01T13:28:37.000Z",
    "valor": 485,
    "unidad": "m3/h",
    "tipo": "caudal_m3_h",
    "participaEnCalculos": true,
    "anomalia": false,
    "motivos": [],
    "scoreAnomalia": 0,
    "valida": {
      "estado": "pendiente",
      "usuario": null,
      "comentario": null,
      "fecha": null
    },
    "historialValidaciones": [],
    "origen": "historico"
  },
  {
    "id": "lectura-0114",
    "sensorId": "sensor-004",
    "division": "Radomiro Tomic",
    "timestamp": "2025-08-01T13:32:07.000Z",
    "valor": 420.408,
    "unidad": "m3/h",
    "tipo": "caudal_m3_h",
    "participaEnCalculos": true,
    "anomalia": false,
    "motivos": [],
    "scoreAnomalia": 0,
    "valida": {
      "estado": "pendiente",
      "usuario": null,
      "comentario": null,
      "fecha": null
    },
    "historialValidaciones": [],
    "origen": "historico"
  },
  {
    "id": "lectura-0115",
    "sensorId": "sensor-004",
    "division": "Radomiro Tomic",
    "timestamp": "2025-08-01T13:36:42.000Z",
    "valor": 430.385,
    "unidad": "m3/h",
    "tipo": "caudal_m3_h",
    "participaEnCalculos": true,
    "anomalia": false,
    "motivos": [],
    "scoreAnomalia": 0,
    "valida": {
      "estado": "pendiente",
      "usuario": null,
      "comentario": null,
      "fecha": null
    },
    "historialValidaciones": [],
    "origen": "historico"
  },
  {
    "id": "lectura-0116",
    "sensorId": "sensor-004",
    "division": "Radomiro Tomic",
    "timestamp": "2025-08-01T13:40:40.000Z",
    "valor": 419.437,
    "unidad": "m3/h",
    "tipo": "caudal_m3_h",
    "participaEnCalculos": true,
    "anomalia": false,
    "motivos": [],
    "scoreAnomalia": 0,
    "valida": {
      "estado": "pendiente",
      "usuario": null,
      "comentario": null,
      "fecha": null
    },
    "historialValidaciones": [],
    "origen": "historico"
  },
  {
    "id": "lectura-0117",
    "sensorId": "sensor-004",
    "division": "Radomiro Tomic",
    "timestamp": "2025-08-01T13:44:04.000Z",
    "valor": 427.94,
    "unidad": "m3/h",
    "tipo": "caudal_m3_h",
    "participaEnCalculos": true,
    "anomalia": false,
    "motivos": [],
    "scoreAnomalia": 0,
    "valida": {
      "estado": "pendiente",
      "usuario": null,
      "comentario": null,
      "fecha": null
    },
    "historialValidaciones": [],
    "origen": "historico"
  },
  {
    "id": "lectura-0118",
    "sensorId": "sensor-004",
    "division": "Radomiro Tomic",
    "timestamp": "2025-08-01T13:48:14.000Z",
    "valor": 365,
    "unidad": "m3/h",
    "tipo": "caudal_m3_h",
    "participaEnCalculos": true,
    "anomalia": false,
    "motivos": [],
    "scoreAnomalia": 0,
    "valida": {
      "estado": "pendiente",
      "usuario": null,
      "comentario": null,
      "fecha": null
    },
    "historialValidaciones": [],
    "origen": "historico"
  },
  {
    "id": "lectura-0119",
    "sensorId": "sensor-004",
    "division": "Radomiro Tomic",
    "timestamp": "2025-08-01T13:52:32.000Z",
    "valor": 426.845,
    "unidad": "m3/h",
    "tipo": "caudal_m3_h",
    "participaEnCalculos": true,
    "anomalia": false,
    "motivos": [],
    "scoreAnomalia": 0,
    "valida": {
      "estado": "pendiente",
      "usuario": null,
      "comentario": null,
      "fecha": null
    },
    "historialValidaciones": [],
    "origen": "historico"
  },
  {
    "id": "lectura-0120",
    "sensorId": "sensor-004",
    "division": "Radomiro Tomic",
    "timestamp": "2025-08-01T13:56:44.000Z",
    "valor": 426.131,
    "unidad": "m3/h",
    "tipo": "caudal_m3_h",
    "participaEnCalculos": true,
    "anomalia": false,
    "motivos": [],
    "scoreAnomalia": 0,
    "valida": {
      "estado": "pendiente",
      "usuario": null,
      "comentario": null,
      "fecha": null
    },
    "historialValidaciones": [],
    "origen": "historico"
  }
]